tradocs/__init__.py
tradocs/tradocs.py
tradocs-1.5.1.dist-info/LICENSE
tradocs-1.5.1.dist-info/METADATA
tradocs-1.5.1.dist-info/WHEEL
tradocs-1.5.1.dist-info/entry_points.txt
tradocs-1.5.1.dist-info/top_level.txt
tradocs-1.5.1.dist-info/RECORD
