Metadata-Version: 2.1
Name: tradocs
Version: 1.5.1
Summary: DocFX localization
Home-page: https://github.com/eberjoe/tradocs
Author: Eber Rodrigues
Author-email: eberjoe@gmail.com
License: MIT
Platform: UNKNOWN
Classifier: Programming Language :: Python :: 3
Classifier: License :: OSI Approved :: MIT License
Classifier: Operating System :: OS Independent
Requires-Python: >=3.6
Requires-Dist: Click
Requires-Dist: gitpython
Requires-Dist: requests
Requires-Dist: colorama
